adt/__init__.py
adt/case.py
adt/decorator.py
adt/mypy_plugin.py
adt/py.typed
algebraic_data_types-0.2.1.dist-info/LICENSE
algebraic_data_types-0.2.1.dist-info/METADATA
algebraic_data_types-0.2.1.dist-info/WHEEL
algebraic_data_types-0.2.1.dist-info/top_level.txt
algebraic_data_types-0.2.1.dist-info/RECORD
