Metadata-Version: 2.1
Name: algebraic-data-types
Version: 0.2.1
Summary: Algebraic data types for Python
Home-page: https://github.com/jspahrsummers/adt
Author: Justin Spahr-Summers
Author-email: justin@jspahrsummers.com
License: MIT
Keywords: adt algebraic data types sum union tagged
Platform: UNKNOWN
Classifier: Development Status :: 3 - Alpha
Classifier: Intended Audience :: Developers
Classifier: License :: OSI Approved :: MIT License
Classifier: Operating System :: OS Independent
Classifier: Programming Language :: Python :: 3 :: Only
Classifier: Programming Language :: Python :: 3.7
Classifier: Programming Language :: Python :: 3
Classifier: Topic :: Software Development :: Libraries :: Python Modules
Classifier: Typing :: Typed
